botox/__init__.py
botox/injector.py
botox_di-1.5.2.dist-info/LICENSE
botox_di-1.5.2.dist-info/METADATA
botox_di-1.5.2.dist-info/WHEEL
botox_di-1.5.2.dist-info/top_level.txt
botox_di-1.5.2.dist-info/RECORD
