Metadata-Version: 2.1
Name: botox-di
Version: 1.5.2
Summary: Botox is a dependency injection implementation based on Python type annotations.
Home-page: https://github.com/lebedec/botox-di
Author: Ilya Lebedev
Author-email: lebedev.games.mail@gmail.com
License: MIT
Project-URL: Code, https://github.com/lebedec/botox-di
Project-URL: Issue tracker, https://github.com/lebedec/botox-di/issues
Platform: any
Classifier: License :: OSI Approved :: MIT License
Classifier: Programming Language :: Python :: 3.6
Classifier: Programming Language :: Python :: 3.7
Classifier: Programming Language :: Python :: 3.8
Classifier: Programming Language :: Python :: 3.9
Classifier: Programming Language :: Python :: 3.10
Requires-Python: >=3.6
License-File: LICENSE
